<?xml version="1.0" encoding="utf-8" ?>
<LanguageData>
	<Watt>Вт</Watt>
	<MinTempMinus>Снижение минимальной комфортной температуры</MinTempMinus>
	<MinTempPlus>Повышение минимальной комфортной температуры</MinTempPlus>
	<MaxTempMinus>Снижение максимальной комфортной температуры</MaxTempMinus>
	<MaxTempPlus>Повышение максимальной комфортной температуры</MaxTempPlus>
	
	<Status>Статус</Status>
	<StatusWaiting>Бездействует</StatusWaiting>
	<StatusHeating>Обогревает</StatusHeating>
	<StatusCooling>Охлаждает</StatusCooling>
	<StatusOutdoor>Установлен снаружи</StatusOutdoor>
	
	<MinComfortTemp>Минимальная комфортная температура</MinComfortTemp>
	<MaxComfortTemp>Максимальная комфортная температура</MaxComfortTemp>
</LanguageData>